cli_rack/__init__.py
cli_rack/__version__.py
cli_rack/ansi.py
cli_rack/cli_extension.py
cli_rack/exception.py
cli_rack/install.py
cli_rack/loader.py
cli_rack/logger.py
cli_rack/modular.py
cli_rack/serialize.py
cli_rack/stats.py
cli_rack/table.py
cli_rack/utils.py
cli_rack_validation/__init__.py
cli_rack_validation/const.py
cli_rack_validation/domain.py
cli_rack_validation/utils.py
cli_rack_validation/validate.py
cli_rack-1.2.0.dist-info/METADATA
cli_rack-1.2.0.dist-info/WHEEL
cli_rack-1.2.0.dist-info/top_level.txt
cli_rack-1.2.0.dist-info/RECORD
