Metadata-Version: 2.1
Name: cli-rack
Version: 1.2.0
Summary: CLI Rack - Lightweight set of tools for building pretty-looking CLI applications in Python
Home-page: https://github.com/corvis/cli-rack
Author: Dmitry Berezovsky
License: MIT
Keywords: python cli terminal modular oop
Classifier: Development Status :: 3 - Alpha
Classifier: Intended Audience :: Developers
Classifier: Topic :: Software Development :: Libraries :: Python Modules
Classifier: Topic :: Home Automation
Classifier: License :: OSI Approved :: MIT License
Classifier: Programming Language :: Python :: 3
Classifier: Programming Language :: Python :: 3.6
Classifier: Programming Language :: Python :: 3.7
Classifier: Programming Language :: Python :: 3.8
Classifier: Programming Language :: Python :: 3.9
Requires-Python: >3.6
Provides-Extra: validation
Requires-Dist: voluptuous==0.12.1; extra == "validation"
